magic_markdown/MagicMarkdown.py
magic_markdown/__init__.py
magic_markdown-1.0.0.dist-info/METADATA
magic_markdown-1.0.0.dist-info/RECORD
magic_markdown-1.0.0.dist-info/WHEEL
magic_markdown-1.0.0.dist-info/top_level.txt
