Metadata-Version: 2.1
Name: magic-markdown
Version: 1.0.0
Summary: IPython cell magic to create markdown cells that contain content from python expressions
Home-page: https://github.com/transfluxus/magic_markdown
Author: Ramin Soleymani
Author-email: transfluxus@posteo.de
License: UNKNOWN
Platform: UNKNOWN
Classifier: Programming Language :: Python
Classifier: License :: OSI Approved :: MIT License
Classifier: Operating System :: OS Independent
Requires-Dist: pystache
Requires-Dist: ipython
